setup.py
micropython_redis.list.egg-info/PKG-INFO
micropython_redis.list.egg-info/SOURCES.txt
micropython_redis.list.egg-info/dependency_links.txt
micropython_redis.list.egg-info/requires.txt
micropython_redis.list.egg-info/top_level.txt
micropython_redis.list.egg-info/zip-safe
uredis_modular/list.py