Metadata-Version: 1.0
Name: micropython-redis.list
Version: 0.0.51
Summary: redis client module for MicroPython
Home-page: https://github.com/dhubbard/micropython-redis
Author: Dwight Hubbard
Author-email: dwight@dwighthubbard.com
License: MIT
Platform: UNKNOWN
